dynafetch/__init__.py
dynafetch/client.py
dynafetch/py.typed
pydynafetch-0.1.0.dist-info/METADATA
pydynafetch-0.1.0.dist-info/WHEEL
pydynafetch-0.1.0.dist-info/licenses/LICENSE
pydynafetch-0.1.0.dist-info/RECORD
