Metadata-Version: 2.4
Name: pydynafetch
Version: 0.1.0
Summary: A python client for Dynamics Business Central OData API
Author-email: akshpra <210279575+akshaypra26@users.noreply.github.com>
License-File: LICENSE
Requires-Python: >=3.12
Requires-Dist: loguru>=0.7.3
Requires-Dist: requests>=2.32.3
